battleship/__init__.py
battleship/__main__.py
battleship/battleship.py
battleship/constants.py
battleship/exceptions.py
battleship/language.py
battleship/main.py
battleship/printer.py
battleship/robot.py
battleship/version.py
tests/__init__.py
tests/conftest.py
tests/test_battleship.py
tests/test_main.py
py_battleship-1.3.2.dist-info/LICENSE
py_battleship-1.3.2.dist-info/METADATA
py_battleship-1.3.2.dist-info/WHEEL
py_battleship-1.3.2.dist-info/entry_points.txt
py_battleship-1.3.2.dist-info/top_level.txt
py_battleship-1.3.2.dist-info/RECORD
