Metadata-Version: 2.1
Name: py-battleship
Version: 1.3.2
Summary: This is a simple, but super cool Battleship game. Lets Play!!!
Home-page: https://github.com/rhenter/battleship-python
Author: Rafael Henter
Author-email: rafael@henter.com.br
License: MIT
Keywords: game battleship board
Platform: UNKNOWN
Classifier: Development Status :: 4 - Beta
Classifier: Intended Audience :: End Users/Desktop
Classifier: License :: OSI Approved :: MIT License
Classifier: Operating System :: OS Independent
Classifier: Programming Language :: Python :: 3.4
Classifier: Programming Language :: Python :: 3.5
Classifier: Programming Language :: Python :: 3.6
Classifier: Programming Language :: Python :: 3.7
Classifier: Programming Language :: Python
Classifier: Topic :: Education
Classifier: Topic :: Games/Entertainment
Classifier: Topic :: Games/Entertainment :: Board Games
Requires-Dist: Click (==7.0)
